{
  "tasks": [
    {
      "id": 1,
      "text": "Doctor's Appointment",
      "day": "May 5th at 2:30pm",
      "reminder": true
    },
    {
      "id": 2,
      "text": "Meeting at School",
      "day": "May 6th at 2:30pm",
      "reminder": true
    },
    {
      "id": 3,
      "text": "Food Shopping",
      "day": "May 7th at 12:30pm",
      "reminder": false
    },
    {
      "id": 4,
      "text": "Return That One Package You Totally Forgot About",
      "day": "May 8th at 4:00pm",
      "reminder": true
    },
    {
      "id": 5,
      "text": "Call Mom (Before She Calls You First)",
      "day": "May 9th at 10:00am",
      "reminder": true
    },
    {
      "id": 6,
      "text": "Water the Plants That Are Judging You",
      "day": "May 10th at 8:00am",
      "reminder": false
    },
    {
      "id": 7,
      "text": "Gym Session — Or At Least Think About Going",
      "day": "May 10th at 6:00pm",
      "reminder": false
    },
    {
      "id": 8,
      "text": "Pay Bills Before They Start Sending Angry Emails",
      "day": "May 11th at 9:00am",
      "reminder": true
    },
    {
      "id": 9,
      "text": "Clean Out the Fridge (Mysterious Container Edition)",
      "day": "May 12th at 3:15pm",
      "reminder": false
    },
    {
      "id": 10,
      "text": "Coffee With Friend You Haven’t Seen in 6 Months",
      "day": "May 13th at 11:00am",
      "reminder": true
    },
    {
      "id": 11,
      "text": "Finally Fix That One Wobbly Chair",
      "day": "May 14th at 1:00pm",
      "reminder": false
    },
    {
      "id": 12,
      "text": "Plan Vacation You Might Actually Take",
      "day": "May 15th at 5:45pm",
      "reminder": true
    }
  ]
}
